autotsk/Controller.py
autotsk/__init__.py
autotsk/__main__.py
autotsk-1.0.1.dist-info/LICENSE.md
autotsk-1.0.1.dist-info/METADATA
autotsk-1.0.1.dist-info/WHEEL
autotsk-1.0.1.dist-info/entry_points.txt
autotsk-1.0.1.dist-info/top_level.txt
autotsk-1.0.1.dist-info/RECORD
