Metadata-Version: 2.1
Name: autotsk
Version: 1.0.1
Summary: Automatically creates mmls, fsstat and fls results for image files
Home-page: https://github.com/5f0ne/autotsk
Author: 5f0
License: MIT
Classifier: Operating System :: OS Independent 
Classifier: Programming Language :: Python :: 3 
Classifier: License :: OSI Approved :: MIT License 
License-File: LICENSE.md
